ao_pyth/__init__.py
ao_pyth/ao_pyth.py
ao_pyth-0.1.6.2.dist-info/licenses/LICENSE.txt
ao_pyth-0.1.6.2.dist-info/METADATA
ao_pyth-0.1.6.2.dist-info/WHEEL
ao_pyth-0.1.6.2.dist-info/top_level.txt
ao_pyth-0.1.6.2.dist-info/RECORD
