Metadata-Version: 2.4
Name: ao_pyth
Version: 0.1.6.2
Summary: AI systems that learn like us, developed by aolabs.ai
Home-page: https://github.com/aolabsai/ao_python
Author: AO Labs
Author-email: AO Labs <eng@aolabs.ai>, Rafayel Latif <rafayel@aolabs.ai>
License: (C) 2025 Animo Omnis Corporation.
Project-URL: Homepage, https://www.aolabs.ai
Project-URL: Bug Tracker, https://github.com/aolabsai/ao_python/issues
Classifier: Development Status :: 3 - Alpha
Classifier: Programming Language :: Python :: 3
Classifier: Operating System :: OS Independent
Classifier: Topic :: Scientific/Engineering :: Artificial Intelligence
Classifier: Topic :: Scientific/Engineering :: Artificial Life
Classifier: Intended Audience :: Developers
Classifier: Intended Audience :: Science/Research
Requires-Python: >=3
License-File: LICENSE.txt
Requires-Dist: requests
Requires-Dist: numpy
Dynamic: author
Dynamic: home-page
Dynamic: license-file
